fastapi_sqlmodel_security/__init__.py
fastapi_sqlmodel_security/_models.py
fastapi_sqlmodel_security/_security_secret.py
fastapi_sqlmodel_security/api_key_security.py
fastapi_sqlmodel_security/data_store.py
fastapi_sqlmodel_security/endpoints.py
fastapi_sqlmodel_security-1.0.1.dist-info/LICENSE
fastapi_sqlmodel_security-1.0.1.dist-info/METADATA
fastapi_sqlmodel_security-1.0.1.dist-info/WHEEL
fastapi_sqlmodel_security-1.0.1.dist-info/RECORD
