Metadata-Version: 2.1
Name: fastapi-sqlmodel-security
Version: 1.0.1
Summary: API key-based security for FastAPI using SQLModel
Home-page: https://github.com/cwang/fastapi_sqlmodel_security
License: MIT
Author: Chen Wang
Author-email: dev@chenwang.org
Requires-Python: >=3.10,<4
Classifier: License :: OSI Approved :: MIT License
Classifier: Programming Language :: Python :: 3
Classifier: Programming Language :: Python :: 3.10
Classifier: Programming Language :: Python :: 3.11
Requires-Dist: fastapi (>=0.70)
Requires-Dist: sqlmodel (>=0.0.14,<0.0.15)
Requires-Dist: urllib3 (>=1.26.12)
Project-URL: Repository, https://github.com/cwang/fastapi_sqlmodel_security
